odoo/addons/website_sale_stock_available_display/README.rst
odoo/addons/website_sale_stock_available_display/__init__.py
odoo/addons/website_sale_stock_available_display/__manifest__.py
odoo/addons/website_sale_stock_available_display/data/demo.xml
odoo/addons/website_sale_stock_available_display/i18n/ca.po
odoo/addons/website_sale_stock_available_display/i18n/de.po
odoo/addons/website_sale_stock_available_display/i18n/es.po
odoo/addons/website_sale_stock_available_display/i18n/fr.po
odoo/addons/website_sale_stock_available_display/i18n/nl.po
odoo/addons/website_sale_stock_available_display/i18n/website_sale_stock_available_display.pot
odoo/addons/website_sale_stock_available_display/models/__init__.py
odoo/addons/website_sale_stock_available_display/models/product_template.py
odoo/addons/website_sale_stock_available_display/models/res_config_settings.py
odoo/addons/website_sale_stock_available_display/readme/CONTRIBUTORS.rst
odoo/addons/website_sale_stock_available_display/readme/DESCRIPTION.rst
odoo/addons/website_sale_stock_available_display/readme/USAGE.rst
odoo/addons/website_sale_stock_available_display/static/description/icon.png
odoo/addons/website_sale_stock_available_display/static/description/index.html
odoo/addons/website_sale_stock_available_display/static/src/js/website_sale_stock_available_display.js
odoo/addons/website_sale_stock_available_display/static/src/js/website_sale_stock_available_display_tour.js
odoo/addons/website_sale_stock_available_display/static/src/xml/website_sale_stock_product_availability.xml
odoo/addons/website_sale_stock_available_display/templates/assets.xml
odoo/addons/website_sale_stock_available_display/templates/templates.xml
odoo/addons/website_sale_stock_available_display/tests/__init__.py
odoo/addons/website_sale_stock_available_display/tests/test_website_sale_stock_available_display.py
odoo/addons/website_sale_stock_available_display/views/assets.xml
odoo13_addon_website_sale_stock_available_display-13.0.1.1.1.dist-info/METADATA
odoo13_addon_website_sale_stock_available_display-13.0.1.1.1.dist-info/WHEEL
odoo13_addon_website_sale_stock_available_display-13.0.1.1.1.dist-info/top_level.txt
odoo13_addon_website_sale_stock_available_display-13.0.1.1.1.dist-info/RECORD
